Han_BackTest/BackTestClass.py
Han_BackTest/DataClass.py
Han_BackTest/FactorClass.py
Han_BackTest/StrategyClass.py
Han_BackTest/__init__.py
Han_BackTest/visualization_config.py
Han_BackTest-1.1.2.dist-info/METADATA
Han_BackTest-1.1.2.dist-info/WHEEL
Han_BackTest-1.1.2.dist-info/top_level.txt
Han_BackTest-1.1.2.dist-info/RECORD
